{
  "name": "Machdyne Noir",
  "class_name": "MachdyneNoirPlatform",
  "vendor": "Lattice",
  "device": "LFE5U-45F-6BG256",
  "package": "",
  "clocks": [
    {
      "name": "clk48",
      "hz": 48000000.0,
      "pin": "A7",
      "is_default": true
    }
  ],
  "default_clock_hz": 48000000.0,
  "leds": [
    {
      "name": "led",
      "number": 0,
      "pins": [
        "C1"
      ],
      "direction": "o",
      "inverted": false,
      "connector": null,
      "attrs": {
        "IOSTANDARD": "LVCMOS33"
      }
    },
    {
      "name": "rgb_led",
      "number": 0,
      "pins": [
        "C1",
        "E1",
        "G1"
      ],
      "direction": "o",
      "inverted": false,
      "connector": null,
      "attrs": {
        "IOSTANDARD": "LVCMOS33"
      }
    },
    {
      "name": "led",
      "number": 1,
      "pins": [
        "E1"
      ],
      "direction": "o",
      "inverted": false,
      "connector": null,
      "attrs": {
        "IOSTANDARD": "LVCMOS33"
      }
    },
    {
      "name": "led",
      "number": 2,
      "pins": [
        "G1"
      ],
      "direction": "o",
      "inverted": false,
      "connector": null,
      "attrs": {
        "IOSTANDARD": "LVCMOS33"
      }
    }
  ],
  "buttons": [],
  "switches": [],
  "seven_seg": null,
  "$schema": "../schema/board.schema.json",
  "source": {
    "origin": "litex-boards",
    "upstream_file": "machdyne_noir.py",
    "sync_commit": "7dda61109d951b6c1ca9cf7331e7a26c0ed84a65",
    "sync_timestamp": "2026-05-25T22:17:21.475851+00:00"
  }
}
